{"id":460,"names":{"chinese":"暴雪王","japanese":"ユキノオー","english":"Abomasnow"},"types":["草","冰"],"species":"树冰","abilities":{"normal":["降雪"],"hidden":["隔音"]},"figure":{"height":2.2,"weight":135.5,"shape":"duofoots","footprint":460},"gender":[50,50],"majorColor":"白色","game":{"catch":60,"egg":{"groups":["怪兽","植物群"],"steps":5140},"base":{"hp":90,"attack":92,"defense":75,"specialAttack":92,"specialDefence":85,"speed":60},"fighting":{"wildExperience":214173,"points":{"hp":0,"attack":1,"defense":0,"specialAttack":1,"specialDefence":0,"speed":0}}},"pokedex":{"5th":{"blackWhite":"当雪花盛开时就会出现，花瓣落下的时候就又不知到了哪里。","blackWhite2":"当雪花盛开时就会出现，花瓣落下的时候就又不知到了哪里。"},"6th":{"x":"会引发暴风雪，让周围变得一片雪白。别名叫冰雪怪物。","y":"静静地生活在万年积雪的山脉。会引发暴风雪来隐藏自己。"}},"gets":{"4th":{"diamond":[{"location":"天冠山顶部","method":"野生","comment":""}],"pearl":[{"location":"天冠山顶部","method":"野生","comment":""}],"platinum":[{"location":"天冠山顶部","method":"野生","comment":""}]},"6th":{"x":[{"location":"１７号道路","method":"野生","comment":""}],"y":[{"location":"１７号道路","method":"野生","comment":""}]},"7th":{"ultraSun":[{"location":"究极空间零地带（黄色时空洞）","method":"野生","comment":""}],"ultraMoon":[{"location":"究极空间零地带（黄色时空洞）","method":"野生","comment":""}]}}}