{"id":401,"names":{"chinese":"圆法师","japanese":"コロボーシ","english":"Kricketot"},"types":["虫"],"species":"蟋蟀","abilities":{"normal":["蜕皮"],"hidden":["逃跑"]},"figure":{"height":0.3,"weight":2.2,"shape":"manlike","footprint":401},"gender":[50,50],"majorColor":"红色","game":{"catch":255,"egg":{"groups":["虫群"],"steps":3855},"base":{"hp":37,"attack":25,"defense":41,"specialAttack":25,"specialDefence":41,"speed":25},"fighting":{"wildExperience":5439,"points":{"hp":0,"attack":0,"defense":1,"specialAttack":0,"specialDefence":0,"speed":0}}},"pokedex":{"5th":{"blackWhite":"腿很短，每当要摔倒的时候就摩擦坚硬的触角，发出木琴一般的声音。","blackWhite2":"腿很短，每当要摔倒的时候就摩擦坚硬的触角，发出木琴一般的声音。"},"6th":{"x":"用互相撞击触角发出的声音和伙伴对话。那音色是秋夜的风景诗。","y":"触角之间互相碰撞的话，就会奏出叮叮咚咚如同木琴一般的音色。"}},"gets":{"4th":{"diamond":[{"location":"２０２号道路，２０３号道路，２０４号道路，２０６号道路，２０７号道路","method":"野生","comment":"夜晨"}],"pearl":[{"location":"２０２号道路，２０３号道路，２０４号道路，２０６号道路，２０７号道路","method":"野生","comment":"夜晨"}],"platinum":[{"location":"２０１号道路，２０２号道路，２０３号道路，２０４号道路，２０５号道路北部，２０７号道路，百代森林","method":"野生","comment":"夜晨"}],"heartGold":[{"location":"自然公园四六","method":"捕虫大赛","comment":"获得全国图鉴后"},{"location":"常磐森林","method":"野生","comment":"大量出现"}],"soulSilver":[{"location":"自然公园四六","method":"捕虫大赛","comment":"获得全国图鉴后"},{"location":"常磐森林","method":"野生","comment":"大量出现"}]},"5th":{"black":[{"location":"","method":"生蛋","comment":"音箱蟀"}],"white":[{"location":"","method":"生蛋","comment":"音箱蟀"}]},"6th":{"omegaRuby":[{"location":"","method":"生蛋","comment":"音箱蟀"}],"alphaSapphire":[{"location":"","method":"生蛋","comment":"音箱蟀"}]}}}