{"id":89,"names":{"chinese":"臭臭泥","japanese":"ベトベトン","english":"Muk"},"types":["毒"],"species":"污泥","abilities":{"normal":["恶臭","黏着","毒手","贪吃鬼"],"hidden":["毒手","化学之力"]},"figure":{"height":1.2,"weight":30,"shape":"duohands","footprint":89},"gender":[50,50],"majorColor":"紫色","game":{"catch":75,"egg":{"groups":["不定形群"],"steps":5140},"base":{"hp":105,"attack":105,"defense":75,"specialAttack":65,"specialDefence":100,"speed":50},"fighting":{"wildExperience":157175,"points":{"hp":1,"attack":1,"defense":0,"specialAttack":0,"specialDefence":0,"speed":0}}},"pokedex":{"1st":{"redGreen":"平时和地面混在一起看不出来。碰到它身体的话会被猛毒侵蚀。","blue":"全身都死死粘着肮脏的淤泥。连只碰到足迹都会被毒侵蚀。","yellow":"非常的臭！可以使人昏厥般强烈，但是臭臭泥的鼻子退化了闻不到味道。"},"2nd":{"gold":"喜欢聚集在污泥堆积发臭的地方，所以那附近会变得更臭。","silver":"全身都是猛毒。不留神碰到的话会发烧卧床不起。","crystal":"臭臭泥通过的痕迹有猛毒渗入，过3年都草木不生。"},"3rd":{"fireRed":"平时和地面混在一起看不出来。碰到它身体的话会被猛毒侵蚀。","leafGreen":"全身都死死粘着肮脏的淤泥。连只碰到足迹都会被毒侵蚀。"},"4th":{"diamondPearlPlatinum":"从身体里会渗出有剧毒的体液。草木一沾上那液体就会瞬间枯萎。","heartGold":"喜欢聚集在污泥堆积发臭的地方，所以那附近会变得更臭。","soulSilver":"全身都是猛毒。不留神碰到的话会发烧卧床不起。"},"5th":{"blackWhite":"从身体里会渗出有剧毒的体液。草木一沾上那液体就会瞬间枯萎。","blackWhite2":"非常臭！身体成份是剧毒的臭臭泥经过的地方所有草木都会枯萎。"},"6th":{"x":"喜欢聚集在污泥堆积发臭的地方，所以那附近会变得更臭。","y":"从身体里会渗出有剧毒的体液。草木一沾上那液体就会瞬间枯萎。"},"7th":{"sun":"总之就是臭得鼻子都不敢呼吸。但是也存在着部分觉得这味道很不错的臭臭泥爱好者。","moon":"在环境治理后的现在，明显已经看不到它们的身影了。据说早晚会灭绝。","ultraSun":"食物变少数量也会急剧减少。为了防止它灭绝，人们开始了制造人工污泥池。","ultraMoon":"因为它会播撒病原菌，所以一直遭到人们的驱逐，结果它的数量也急剧减少了。"}},"gets":{"1st":{"red":[{"location":"宝可梦屋","method":"野生","comment":""}],"green":[{"location":"宝可梦屋","method":"野生","comment":""}],"blue":[{"location":"宝可梦屋","method":"野生","comment":""}],"yellow":[{"location":"宝可梦屋，无人发电厂","method":"野生","comment":""},{"location":"宝可梦研究所","method":"用袋兽交换*","comment":""}]},"2nd":{"gold":[{"location":"１６号道路，１７号道路，１８号道路","method":"野生","comment":""},{"location":"彩虹市","method":"冲浪","comment":""}],"silver":[{"location":"１６号道路，１７号道路，１８号道路","method":"野生","comment":""},{"location":"彩虹市","method":"冲浪","comment":""}],"crystal":[{"location":"１６号道路，１７号道路，１８号道路","method":"野生","comment":""},{"location":"彩虹市","method":"冲浪","comment":""}]},"3rd":{"ruby":[{"location":"","method":"进化","comment":"臭泥"}],"sapphire":[{"location":"","method":"进化","comment":"臭泥"}],"emerald":[{"location":"","method":"进化","comment":"臭泥"}],"fireRed":[{"location":"","method":"进化","comment":"臭泥"}],"leafGreen":[{"location":"宝可梦屋","method":"野生","comment":""}]},"4th":{"diamond":[{"location":"","method":"进化","comment":"臭泥"}],"pearl":[{"location":"","method":"进化","comment":"臭泥"}],"platinum":[{"location":"","method":"进化","comment":"臭泥"}],"heartGold":[{"location":"１６号道路，１７号道路，１８号道路","method":"野生","comment":""},{"location":"彩虹市","method":"冲浪","comment":""}],"soulSilver":[{"location":"１６号道路，１７号道路，１８号道路","method":"野生","comment":""},{"location":"彩虹市","method":"冲浪","comment":""}]},"5th":{"black2":[{"location":"９号道路","method":"野生","comment":""},{"location":"９号道路","method":"隐藏洞穴","comment":"毒手"},{"location":"飞云地下水道春夏","method":"水纹水面（冲浪/垂钓）","comment":""}],"white2":[{"location":"９号道路","method":"野生","comment":""},{"location":"９号道路","method":"隐藏洞穴","comment":"毒手"},{"location":"飞云地下水道春夏","method":"水纹水面（冲浪/垂钓）","comment":""}]},"6th":{"x":[{"location":"朋友狩猎（毒属性）","method":"野生","comment":""}],"y":[{"location":"朋友狩猎（毒属性）","method":"野生","comment":""}],"omegaRuby":[{"location":"","method":"进化","comment":"臭泥"}],"alphaSapphire":[{"location":"","method":"进化","comment":"臭泥"}]},"7th":{"sun":[{"location":"","method":"进化","comment":"臭泥，阿罗拉的样子"}],"moon":[{"location":"","method":"进化","comment":"臭泥，阿罗拉的样子"}],"ultraSun":[{"location":"","method":"进化","comment":"臭泥，阿罗拉的样子"}],"ultraMoon":[{"location":"","method":"进化","comment":"臭泥，阿罗拉的样子"}]}}}