{"id":616,"names":{"chinese":"小嘴蜗","japanese":"チョボマキ","english":"Shelmet"},"types":["虫"],"species":"蜗牛","abilities":{"normal":["湿润之躯","硬壳盔甲"],"hidden":["防尘"]},"figure":{"height":0.4,"weight":7.7,"shape":"ball","footprint":616},"gender":[50,50],"majorColor":"红色","game":{"catch":200,"egg":{"groups":["虫群"],"steps":3855},"base":{"hp":50,"attack":40,"defense":85,"specialAttack":40,"specialDefence":65,"speed":25},"fighting":{"wildExperience":61,"points":{"hp":0,"attack":0,"defense":1,"specialAttack":0,"specialDefence":0,"speed":0}}},"pokedex":{"5th":{"blackWhite2":"与盖盖虫在一起时，如果受到电的刺激，双方的身体就会进化。"},"6th":{"x":"与盖盖虫在一起时，如果受到电的刺激，双方的身体就会进化。","y":"如果与盖盖虫一起沐浴在电能下，就会进化。其原因尚且不明。"}},"gets":{"5th":{"black":[{"location":"８号道路春夏秋、雪花市春夏秋、雪花湿地春夏秋","method":"野生","comment":""}],"white":[{"location":"８号道路春夏秋、雪花市春夏秋、雪花湿地春夏秋","method":"野生","comment":""}],"black2":[{"location":"６号道路、１１号道路、８号道路春夏秋、雪花市春夏秋、雪花湿地春夏秋","method":"野生","comment":""}],"white2":[{"location":"６号道路、１１号道路、８号道路春夏秋、雪花市春夏秋、雪花湿地春夏秋","method":"野生","comment":""}]},"6th":{"x":[{"location":"１４号道路、１９号道路","method":"野生","comment":""}],"y":[{"location":"１４号道路、１９号道路","method":"野生","comment":""}]}}}