{"id":208,"names":{"chinese":"大钢蛇","japanese":"ハガネール","english":"Steelix"},"types":["钢","地面"],"species":"铁蛇","abilities":{"normal":["坚硬脑袋","结实","沙之力"],"hidden":["强行"]},"figure":{"height":9.2,"weight":400,"shape":"snake","footprint":208},"gender":[50,50],"majorColor":"灰色","game":{"catch":25,"egg":{"groups":["矿物群"],"steps":6425},"base":{"hp":75,"attack":85,"defense":200,"specialAttack":55,"specialDefence":65,"speed":30},"fighting":{"wildExperience":196179,"points":{"hp":0,"attack":0,"defense":2,"specialAttack":0,"specialDefence":0,"speed":0}}},"pokedex":{"2nd":{"gold":"在深层地底经过压缩的身体比钻石还要坚硬。","silver":"据说大岩蛇活了一百年以上，身体的成分就会变成如同钻石一般。","crystal":"覆盖全身的钢铁的碎片黏在一起， 反射出闪烁的光芒。"},"3rd":{"rubySapphireEmerald":"在地下住得比大岩蛇还深。会朝着地球的中心挖掘，有时洞深可达１公里。","fireRed":"据说大岩蛇活了一百年以上，身体的成分就会变成如同钻石一般。","leafGreen":"在深层地底经过压缩的身体比钻石还要坚硬。"},"4th":{"heartGold":"在深层地底经过压缩的身体比钻石还要坚硬。","soulSilver":"据说大岩蛇活了一百年以上，身体的成分就会变成如同钻石一般。"},"5th":{"blackWhite":"一般认为是和泥土一起吞下的钢铁积存起来，身体才会发生变化。","blackWhite2":"随泥土一起吞下的钢铁让身体发生了变化，变得比钻石更坚硬。"},"6th":{"x":"由地下高压和高热锻炼出来的身体比任何金属都要坚硬。","y":"会用结实的颚咬碎岩石前进。有着即使是在漆黑的地下也能看清东西的眼睛。","omegaRubyAlphaSapphire":"在地下住得比大岩蛇还深。会朝着地球的中心挖掘，有时洞深可达１公里。"}},"gets":{"2nd":{"gold":[{"location":"携带金属膜通讯进化","method":"大岩蛇","comment":""}],"silver":[{"location":"携带金属膜通讯进化","method":"大岩蛇","comment":""}],"crystal":[{"location":"携带金属膜通讯进化","method":"大岩蛇","comment":""}]},"3rd":{"fireRed":[{"location":"携带金属膜通讯进化","method":"大岩蛇","comment":""}],"leafGreen":[{"location":"携带金属膜通讯进化","method":"大岩蛇","comment":""}]},"4th":{"diamond":[{"location":"钢铁岛、切锋神殿、冠军之路","method":"野生","comment":""}],"pearl":[{"location":"钢铁岛、切锋神殿、冠军之路","method":"野生","comment":""}],"platinum":[{"location":"钢铁岛、冠军之路","method":"野生","comment":""}],"heartGold":[{"location":"白银山、断崖洞窟","method":"野生","comment":""},{"location":"浅黄市","method":"用任意宝可梦与阿蜜交换*","comment":"在格斗道场击败阿蜜后，安抚之铃"}],"soulSilver":[{"location":"白银山、断崖洞窟","method":"野生","comment":""},{"location":"浅黄市","method":"用任意宝可梦与阿蜜交换*","comment":"在格斗道场击败阿蜜后，安抚之铃"}]},"5th":{"black":[{"location":"携带金属膜通讯进化","method":"大岩蛇","comment":""}],"white":[{"location":"携带金属膜通讯进化","method":"大岩蛇","comment":""}],"black2":[{"location":"罗斯山、菊老大路、地底遗迹","method":"卷尘地面","comment":""}],"white2":[{"location":"罗斯山、菊老大路、地底遗迹","method":"卷尘地面","comment":""}]},"6th":{"x":[{"location":"遥香市","method":"用爱心鱼交换*","comment":""}],"y":[{"location":"遥香市","method":"用爱心鱼交换*","comment":""}],"omegaRuby":[{"location":"携带金属膜通讯进化","method":"大岩蛇","comment":""}],"alphaSapphire":[{"location":"携带金属膜通讯进化","method":"大岩蛇","comment":""}]},"7th":{"ultraSun":[{"location":"携带金属膜通讯进化","method":"大岩蛇","comment":""}],"ultraMoon":[{"location":"携带金属膜通讯进化","method":"大岩蛇","comment":""}]}}}