{"id":666,"names":{"chinese":"彩粉蝶","japanese":"ビビヨン","english":"Vivillon"},"types":["虫","飞行"],"species":"鳞粉","abilities":{"normal":["鳞粉","复眼"],"hidden":["友情防守"]},"figure":{"height":1.2,"weight":17,"shape":"mulwings","footprint":null},"gender":[50,50],"majorColor":"白色","game":{"catch":45,"egg":{"groups":["虫群"],"steps":3855},"base":{"hp":80,"attack":52,"defense":50,"specialAttack":90,"specialDefence":50,"speed":89},"fighting":{"wildExperience":185,"points":{"hp":0,"attack":0,"defense":0,"specialAttack":3,"specialDefence":0,"speed":0}}},"pokedex":{"6th":{"x":"世界上有着各种各样翅膀花纹的彩粉蝶。好像是受所居住土地的气候影响。","y":"根据所居住地区的气候和水土，翅膀花纹各不相同的宝可梦。会撒出色彩鲜艳的鳞粉。"}},"gets":{"6th":{"x":[{"location":"朋友狩猎（虫属性）","method":"野生","comment":""}],"y":[{"location":"朋友狩猎（虫属性）","method":"野生","comment":""}]},"7th":{"ultraSun":[{"location":"","method":"进化","comment":"粉蝶蛹"}],"ultraMoon":[{"location":"","method":"进化","comment":"粉蝶蛹"}]}}}