{"id":399,"names":{"chinese":"大牙狸","japanese":"ビッパ","english":"Bidoof"},"types":["一般"],"species":"圆鼠","abilities":{"normal":["单纯","纯朴"],"hidden":["心情不定"]},"figure":{"height":0.5,"weight":20,"shape":"quafoots","footprint":399},"gender":[50,50],"majorColor":"褐色","game":{"catch":255,"egg":{"groups":["水中1","陆上群"],"steps":3855},"base":{"hp":59,"attack":45,"defense":40,"specialAttack":35,"specialDefence":40,"speed":31},"fighting":{"wildExperience":5850,"points":{"hp":1,"attack":0,"defense":0,"specialAttack":0,"specialDefence":0,"speed":0}}},"pokedex":{"5th":{"blackWhite":"经过比较，人们发现大牙狸和小拉达的门牙生长速度不相上下。","blackWhite2":"经过比较，人们发现它和小拉达的门牙生长速度不相上下。"},"6th":{"x":"遇到任何事都不慌不忙，神经很大条的家伙。能做出与外表不符的灵敏动作。","y":"总是啃大树和石头来磨结实的门牙。在水边筑巢生活。"}},"gets":{"4th":{"diamond":[{"location":"道路（201・202・203・204・205・208・211），心齐湖，山谷发电厂，大湿地","method":"野生","comment":""}],"pearl":[{"location":"道路（201・202・203・204・205・208・211），心齐湖，山谷发电厂，大湿地","method":"野生","comment":""}],"platinum":[{"location":"道路（201・202・203・204・205・208・211），心齐湖，百代森林","method":"野生","comment":""}],"heartGold":[{"location":"道路（4・6・9・10・13・21・22・24・25・26・27・28・30・31・32・34・35・42・43・44・45・47），阿露福遗迹，白银山外部","method":"野生","comment":"神奥之声"}],"soulSilver":[{"location":"道路（4・6・9・10・13・21・22・24・25・26・27・28・30・31・32・34・35・42・43・44・45・47），阿露福遗迹，白银山外部","method":"野生","comment":"神奥之声"}]},"5th":{"black":[{"location":"","method":"生蛋","comment":"大尾狸"}],"white":[{"location":"","method":"生蛋","comment":"大尾狸"}],"black2":[{"location":"","method":"生蛋","comment":"大尾狸"}],"white2":[{"location":"","method":"生蛋","comment":"大尾狸"}]},"6th":{"x":[{"location":"３号道路,２２号道路","method":"野生","comment":""}],"y":[{"location":"３号道路,２２号道路","method":"野生","comment":""}]}}}