{"id":433,"names":{"chinese":"铃铛响","japanese":"リーシャン","english":"Chingling"},"types":["超能力"],"species":"铃铛","abilities":{"normal":["飘浮"],"hidden":[]},"figure":{"height":0.2,"weight":0.6,"shape":"manlike","footprint":433},"gender":[50,50],"majorColor":"黄色","game":{"catch":120,"egg":{"groups":["未发现群"],"steps":6425},"base":{"hp":45,"attack":30,"defense":50,"specialAttack":65,"specialDefence":50,"speed":45},"fighting":{"wildExperience":7457,"points":{"hp":0,"attack":0,"defense":0,"specialAttack":1,"specialDefence":0,"speed":0}}},"pokedex":{"5th":{"blackWhite":"如果跳起来，嘴里的珠子就会弹来弹去，发出铃铛一般的音色。","blackWhite2":"如果跳起来，嘴里的珠子就会弹来弹去，发出铃铛一般的音色。"},"6th":{"x":"每次跳跃都会发出铃铃声。用高频率的叫声让对手失聪。","y":"如果跳起来，嘴里的珠子就会弹来弹去，发出铃铛一般的音色。"}},"gets":{"4th":{"diamond":[{"location":"２１１号道路，天冠山，立志湖，睿智湖","method":"野生","comment":""}],"pearl":[{"location":"２１１号道路，天冠山，立志湖，睿智湖","method":"野生","comment":""}],"platinum":[{"location":"２１１号道路，天冠山，送泉，归途洞窟","method":"野生","comment":""}],"heartGold":[{"location":"漩涡列岛，黑暗穴，冰雪通路，擂钵山，断崖洞窟，互连洞，呆呆兽之井，","method":"岩山隧道，月见山，白银山，冠军之路，地鼠洞穴，都城瀑布，华蓝洞窟，双子岛","comment":"野生"},{"location":"狩猎地带（山峰）","method":"野生","comment":""}],"soulSilver":[{"location":"漩涡列岛，黑暗穴，冰雪通路，擂钵山，断崖洞窟，互连洞，呆呆兽之井，","method":"岩山隧道，月见山，白银山，冠军之路，地鼠洞穴，都城瀑布，华蓝洞窟，双子岛","comment":"野生"},{"location":"狩猎地带（山峰）","method":"野生","comment":""}]},"5th":{"black":[{"location":"携带洁净薰香生蛋","method":"风铃铃♀","comment":""}],"white":[{"location":"携带洁净薰香生蛋","method":"风铃铃♀","comment":""}]},"6th":{"x":[{"location":"１１号道路、镜穴","method":"野生","comment":""}],"y":[{"location":"１１号道路、镜穴","method":"野生","comment":""}],"omegaRuby":[{"location":"携带洁净薰香生蛋","method":"风铃铃","comment":""}],"alphaSapphire":[{"location":"携带洁净薰香生蛋","method":"风铃铃","comment":""}]}}}