{"id":451,"names":{"chinese":"钳尾蝎","japanese":"スコルピ","english":"Skorupi"},"types":["毒","虫"],"species":"蝎子","abilities":{"normal":["战斗盔甲","狙击手"],"hidden":["锐利目光"]},"figure":{"height":0.8,"weight":12,"shape":"bug","footprint":451},"gender":[50,50],"majorColor":"紫色","game":{"catch":120,"egg":{"groups":["虫","水中3群"],"steps":5140},"base":{"hp":40,"attack":50,"defense":90,"specialAttack":30,"specialDefence":55,"speed":65},"fighting":{"wildExperience":11466,"points":{"hp":0,"attack":0,"defense":1,"specialAttack":0,"specialDefence":0,"speed":0}}},"pokedex":{"5th":{"blackWhite":"当尾巴上的钳子闭合后，会从针尖渗出毒素。可以不吃东西存活１年。","blackWhite2":"生活在干燥的土地上，可以一年到头什么都不吃地伏击猎物。"},"6th":{"x":"用尾巴上的钩爪夹住猎物并注入毒素。很执着，毒不发作就绝不松开。","y":"躲藏在沙子中伏击猎物。从尾巴上的钩爪放出毒素，了结猎物。"}},"gets":{"4th":{"diamond":[{"location":"大湿地","method":"野生","comment":""}],"pearl":[{"location":"大湿地","method":"野生","comment":""}],"platinum":[{"location":"大湿地","method":"野生","comment":""}],"heartGold":[{"location":"狩猎地带（荒地区域）","method":"野生","comment":""}],"soulSilver":[{"location":"狩猎地带（荒地区域）","method":"野生","comment":""}]},"5th":{"black2":[{"location":"反转山","method":"野生","comment":""},{"location":"１３号道路","method":"隐藏洞穴","comment":"锐利目光"}],"white2":[{"location":"反转山","method":"野生","comment":""},{"location":"１３号道路","method":"隐藏洞穴","comment":"锐利目光"}]},"6th":{"x":[{"location":"１４号道路、１５号道路、１６号道路","method":"野生","comment":""},{"location":"１４号道路","method":"群聚对战","comment":""}],"y":[{"location":"１４号道路、１５号道路、１６号道路","method":"野生","comment":""},{"location":"１４号道路","method":"群聚对战","comment":""}],"omegaRuby":[{"location":"１１４号道路","method":"忍足系统","comment":"固拉多ΩR/盖欧卡αS事件解决之后"}],"alphaSapphire":[{"location":"１１４号道路","method":"忍足系统","comment":"固拉多ΩR/盖欧卡αS事件解决之后"}]},"7th":{"ultraSun":[{"location":"","method":"生蛋","comment":"龙王蝎"}],"ultraMoon":[{"location":"","method":"生蛋","comment":"龙王蝎"}]}}}